{"about_index.md":"BSN7tIBv","about_me.md":"DM973pnv","archives.md":"9xnkzU_6","categories_annals_2024_02_10_第二版博客搭建完成.md":"38waVsqa","categories_annals_2024_02_11_新年快乐.md":"CpRxE1pB","categories_annals_2024_05_05_第三版博客搭建完成.md":"Bf8fLTEm","categories_annals_2024_05_11_第四版博客新题性.md":"BYfqS2g3","categories_annals_2024_05_23_第五版博客发布完成.md":"BkKHZcRw","categories_annals_2024_05_26_ha综合布线.md":"B9Rzgtbc","categories_annals_2024_05_29_打印机共享.md":"DV_3QsHt","categories_annals_2024_06_02_性能优化.md":"H0tWNJiF","categories_annals_2024_06_03_excel大小优化.md":"DsTq7kUy","categories_annals_2024_06_10_更好的svg集成.md":"BTFUXAmX","categories_annals_2024_06_17_商业报告模板.md":"D6XxRjDk","categories_annals_2024_08_18_第六版博客发布.md":"C9FZnoMz","categories_annals_2024_11_23_第七版博客发布.md":"tePC_QBI","categories_annals_2024_11_25_开始记录生活.md":"CB7IBtvR","categories_annals_2024_11_26_周二的一天.md":"BQK2hY6_","categories_annals_2024_11_27_daily notes.md":"C769gL0c","categories_annals_2024_11_28_防火墙学习.md":"D9JFCED4","categories_annals_2024_11_29_萤石云app接入.md":"DYc1VoJR","categories_annals_2024_12_01_默认路由.md":"BZVETidE","categories_annals_2024_12_02_加班处理考勤掉线.md":"BDjrfK_8","categories_annals_2024_12_04_局域网路由.md":"DZaR1onj","categories_annals_2024_12_12_最近日常.md":"DMl7X4e-","categories_annals_2024_index.md":"DV8suw_5","categories_annals_2025_01_01_云贵之旅.md":"BKEaf-HX","categories_annals_2025_01_02_新一年，新篇章.md":"C_OFE-3V","categories_annals_2025_01_05_第八版博客发布.md":"Cndze69v","categories_annals_2025_01_12_双栏布局.md":"Da-tH_jV","categories_annals_2025_01_16_工作日常.md":"DEa6YrdW","categories_annals_2025_index.md":"D6SysRne","categories_annals_index.md":"CG3mXcyH","courses_java_01-java语法入门_01-开发环境搭建.md":"BivJTqsa","courses_java_01-java语法入门_test.md":"BzUvHeDF","courses_java_index.md":"C8p5uW2D","docs_index.md":"4-TfjPEK","index.md":"GMRkQl64","nav_index.md":"vAJ6KUpF","tags.md":"BBUsPmQJ"}
